winregistry.py
winregistry-2.1.2.dist-info/METADATA
winregistry-2.1.2.dist-info/WHEEL
winregistry-2.1.2.dist-info/licenses/LICENSE
winregistry-2.1.2.dist-info/RECORD
