Metadata-Version: 2.4
Name: winregistry
Version: 2.1.2
Summary: A Python library for interacting with the Windows registry
Project-URL: Homepage, https://github.com/shpaker/winregistry/
Project-URL: Repository, https://github.com/shpaker/winregistry/
Author-email: Aleksandr Shpak <shpaker@gmail.com>
License-Expression: MIT
License-File: LICENSE
Keywords: regedit,registry,windows,winreg
Classifier: Framework :: Robot Framework :: Library
Classifier: Operating System :: Microsoft :: Windows
Classifier: Programming Language :: Python
Classifier: Programming Language :: Python :: 3 :: Only
Classifier: Programming Language :: Python :: 3.8
Classifier: Programming Language :: Python :: 3.9
Classifier: Programming Language :: Python :: 3.10
Classifier: Programming Language :: Python :: 3.11
Classifier: Programming Language :: Python :: 3.12
Classifier: Programming Language :: Python :: 3.13
Classifier: Programming Language :: Python :: 3.14
Requires-Python: >=3.8
